{
    "sourceFile": "globalpresence/serializers/globalpresence_serializers.py",
    "activeCommit": 0,
    "commits": [
        {
            "activePatchIndex": 7,
            "patches": [
                {
                    "date": 1730266790277,
                    "content": "Index: \n===================================================================\n--- \n+++ \n"
                },
                {
                    "date": 1730272775150,
                    "content": "Index: \n===================================================================\n--- \n+++ \n@@ -15,4 +15,23 @@\n     class Meta:\n         model = GlobalPresence\n         fields = '__all__'\n         \n+    def update(self, instance, validated_data):\n+        # Handle the media field separately\n+        media = validated_data.pop('media', None)\n+\n+        if media is not None:\n+            if media == \"null\":\n+                # If media is set to 'null', delete the current media\n+                instance.media.delete(save=False)\n+                instance.media = None\n+            else:\n+                # If media data is sent, update it\n+                instance.media = media\n+\n+        # Update other fields\n+        for attr, value in validated_data.items():\n+            setattr(instance, attr, value)\n+\n+        instance.save()\n+        return instance\n\\ No newline at end of file\n"
                },
                {
                    "date": 1731320602750,
                    "content": "Index: \n===================================================================\n--- \n+++ \n@@ -1,7 +1,12 @@\n from rest_framework import serializers\n from ..models import GlobalPresence\n \n+class CountryListSerializers(serializers.ModelSerializer):\n+    class Meta:\n+        model = Country\n+        fields = '__all__'\n+        \n class GlobalPresenceListSerializers(serializers.ModelSerializer):\n     class Meta:\n         model = GlobalPresence\n         fields = '__all__'\n"
                },
                {
                    "date": 1731320610546,
                    "content": "Index: \n===================================================================\n--- \n+++ \n@@ -1,8 +1,8 @@\n from rest_framework import serializers\n-from ..models import GlobalPresence\n+from ..models import GlobalPresence,Country\n \n-class CountryListSerializers(serializers.ModelSerializer):\n+class CountrySerializers(serializers.ModelSerializer):\n     class Meta:\n         model = Country\n         fields = '__all__'\n         \n"
                },
                {
                    "date": 1731320684089,
                    "content": "Index: \n===================================================================\n--- \n+++ \n@@ -6,8 +6,9 @@\n         model = Country\n         fields = '__all__'\n         \n class GlobalPresenceListSerializers(serializers.ModelSerializer):\n+    country = CountrySerializer(read_only=True)  \n     class Meta:\n         model = GlobalPresence\n         fields = '__all__'\n \n"
                },
                {
                    "date": 1731320691377,
                    "content": "Index: \n===================================================================\n--- \n+++ \n@@ -6,9 +6,9 @@\n         model = Country\n         fields = '__all__'\n         \n class GlobalPresenceListSerializers(serializers.ModelSerializer):\n-    country = CountrySerializer(read_only=True)  \n+    country = CountrySerializers(read_only=True)  \n     class Meta:\n         model = GlobalPresence\n         fields = '__all__'\n \n@@ -17,8 +17,9 @@\n         model = GlobalPresence\n         fields = '__all__'\n \n class GlobalPresenceWriteSerializers(serializers.ModelSerializer):\n+    country = CountrySerializers(read_only=True)  \n     class Meta:\n         model = GlobalPresence\n         fields = '__all__'\n         \n"
                },
                {
                    "date": 1731320696989,
                    "content": "Index: \n===================================================================\n--- \n+++ \n@@ -12,8 +12,9 @@\n         model = GlobalPresence\n         fields = '__all__'\n \n class GlobalPresenceRetrieveSerializers(serializers.ModelSerializer):\n+    country = CountrySerializers(read_only=True)  \n     class Meta:\n         model = GlobalPresence\n         fields = '__all__'\n \n"
                },
                {
                    "date": 1731320702189,
                    "content": "Index: \n===================================================================\n--- \n+++ \n@@ -18,9 +18,8 @@\n         model = GlobalPresence\n         fields = '__all__'\n \n class GlobalPresenceWriteSerializers(serializers.ModelSerializer):\n-    country = CountrySerializers(read_only=True)  \n     class Meta:\n         model = GlobalPresence\n         fields = '__all__'\n         \n"
                }
            ],
            "date": 1730266790277,
            "name": "Commit-0",
            "content": "from rest_framework import serializers\nfrom ..models import GlobalPresence\n\nclass GlobalPresenceListSerializers(serializers.ModelSerializer):\n    class Meta:\n        model = GlobalPresence\n        fields = '__all__'\n\nclass GlobalPresenceRetrieveSerializers(serializers.ModelSerializer):\n    class Meta:\n        model = GlobalPresence\n        fields = '__all__'\n\nclass GlobalPresenceWriteSerializers(serializers.ModelSerializer):\n    class Meta:\n        model = GlobalPresence\n        fields = '__all__'\n        \n"
        }
    ]
}